aaaawslogger/__init__.py
aaaawslogger/aws_logger.py
aaaawslogger/aws_logger_constants.py
aaaawslogger/awslogger.py
aaaawslogger/splunk.py
aceagentaws/__init__.py
aceagentaws/mongodb_vector_store.py
aceagentaws/secrets_manager.py
aceagentlogger/__init__.py
aceagentlogger/aws_logger.py
aceagentlogger/aws_logger_constants.py
aceagentlogger/splunk.py
aws_logger/__init__.py
aws_logger/aws_logger.py
aws_logger_project/__init__.py
aws_logger_project/aws_logger.py
build/lib/aaaawslogger/__init__.py
build/lib/aaaawslogger/aws_logger.py
build/lib/aaaawslogger/aws_logger_constants.py
build/lib/aaaawslogger/awslogger.py
build/lib/aaaawslogger/splunk.py
build/lib/aceagentaws/__init__.py
build/lib/aceagentaws/mongodb_vector_store.py
build/lib/aceagentaws/secrets_manager.py
build/lib/aceagentlogger/__init__.py
build/lib/aceagentlogger/aws_logger.py
build/lib/aceagentlogger/aws_logger_constants.py
build/lib/aceagentlogger/splunk.py
build/lib/aws_logger/__init__.py
build/lib/aws_logger/aws_logger.py
build/lib/aws_logger_project/__init__.py
build/lib/aws_logger_project/aws_logger.py
build/lib/build/lib/aaaawslogger/__init__.py
build/lib/build/lib/aaaawslogger/aws_logger.py
build/lib/build/lib/aaaawslogger/aws_logger_constants.py
build/lib/build/lib/aaaawslogger/awslogger.py
build/lib/build/lib/aaaawslogger/splunk.py
build/lib/build/lib/aceagentaws/__init__.py
build/lib/build/lib/aceagentaws/mongodb_vector_store.py
build/lib/build/lib/aceagentaws/secrets_manager.py
build/lib/build/lib/aceagentlogger/__init__.py
build/lib/build/lib/aceagentlogger/aws_logger.py
build/lib/build/lib/aceagentlogger/aws_logger_constants.py
build/lib/build/lib/aceagentlogger/splunk.py
build/lib/build/lib/aws_logger/__init__.py
build/lib/build/lib/aws_logger/aws_logger.py
build/lib/build/lib/aws_logger_project/__init__.py
build/lib/build/lib/aws_logger_project/aws_logger.py
build/lib/build/lib/build/lib/aaaawslogger/__init__.py
build/lib/build/lib/build/lib/aaaawslogger/aws_logger.py
aceagentaws-0.0.4.dist-info/METADATA
aceagentaws-0.0.4.dist-info/WHEEL
aceagentaws-0.0.4.dist-info/top_level.txt
aceagentaws-0.0.4.dist-info/RECORD
