Metadata-Version: 2.1
Name: aceagentaws
Version: 0.0.4
Summary: Logger
Author: ace
Author-email: kardaras.george@clublabs.com
Requires-Dist: boto3
Requires-Dist: aceagentlogger
